connalysis/__init__.py
connalysis/modelling/__init__.py
connalysis/modelling/modelling.py
connalysis/network/__init__.py
connalysis/network/classic.py
connalysis/network/local.py
connalysis/network/stats.py
connalysis/network/topology.py
connalysis/randomization/__init__.py
connalysis/randomization/rand_utils.py
connalysis/randomization/randomization.py
connectome_analysis-1.0.2.dist-info/LICENCE
connectome_analysis-1.0.2.dist-info/METADATA
connectome_analysis-1.0.2.dist-info/WHEEL
connectome_analysis-1.0.2.dist-info/RECORD
