Metadata-Version: 2.3
Name: connectome_analysis
Version: 1.0.2
Summary: Methods for network analysis of graphs coming from brain models and activity on them
License: AGPL-3.0-or-later
Author: Daniela Egas Santander
Author-email: daniela.egas.math@gmail.com
Requires-Python: >=3.9,<3.13
Classifier: Development Status :: 4 - Beta
Classifier: Intended Audience :: Developers
Classifier: License :: OSI Approved :: GNU Affero General Public License v3 or later (AGPLv3+)
Classifier: Operating System :: OS Independent
Classifier: Programming Language :: Python
Classifier: Programming Language :: Python :: 3
Classifier: Programming Language :: Python :: 3.9
Classifier: Programming Language :: Python :: 3.10
Classifier: Programming Language :: Python :: 3.11
Classifier: Programming Language :: Python :: 3.12
Classifier: Programming Language :: Python :: 3.8
Classifier: Topic :: Software Development :: Libraries :: Python Modules
Classifier: Typing :: Typed
Requires-Dist: bigrandomgraphs (>=0.0.4)
Requires-Dist: ipykernel (>=6.29.5,<7.0.0)
Requires-Dist: matplotlib
Requires-Dist: networkx
Requires-Dist: numpy
Requires-Dist: pandas
Requires-Dist: progressbar (==2.5)
Requires-Dist: pyflagser
Requires-Dist: pyflagsercount (>=0.2.41)
Requires-Dist: scikit-network
Requires-Dist: scipy
Requires-Dist: tables (>3.8)
Requires-Dist: tqdm
Project-URL: Documentation, https://openbraininstitute.github.io/connectome-analysis/
Project-URL: Homepage, https://openbraininstitute.github.io/connectome-analysis/
Project-URL: Repository, https://github.com/openbraininstitute/connectome-analysis.git
